musicbox/musicbox.v
module music(clk, speaker);
 initial
  begin
     $dumpfile("musicbox.vcd");
     $dumpvars(0,music);
  end
   
  input clk;
  output speaker;
   
  reg [14:0] counter;
   initial begin
   counter[14:0] <= 0;
   speaker <=0;   
   end
   always @(posedge clk) 
     if(counter==28408) 
       counter <=0; 
     else
       counter <=(counter+1);
       initial begin
       //$monitor("cntr= %d \n", counter[14:0]);
       end

   reg speaker;
   always @(posedge clk) 
     if(counter==28408)  
       speaker <= ~speaker;
   
endmodule

musicbox/testfile.v

`timescale 1ns/1ps
module testfile;
   reg clk;
   wire speaker;

   music spkr(.clk(clk), .speaker(speaker));
   initial begin
      $dumpfile("testfile.vcd");
      $dumpvars(0, testfile);
      clk <=0;      
   end

   always begin//creates running clock and prints statuses
      #40 clk = ~clk;
      $monitor("t = %d, clk = %b, spkr = %d\n", $time, clk, speaker);
      //stops after certain time
      if($time >= 1000000000)//1 second
	$finish(1);
   end
endmodule

musicbox/musicbox.vcd
$date
	Tue Jun 14 13:05:30 2016
$end
$version
	Icarus Verilog
$end
$timescale
	1ps
$end
$scope module testfile $end
$scope module spkr $end
$var wire 1 ! clk $end
$var reg 15 " counter [14:0] $end
$var reg 1 # speaker $end
$upscope $end
$upscope $end
$scope module testfile $end
$var wire 1 $ speaker $end
$var reg 1 % clk $end
$scope module spkr $end
$upscope $end
$upscope $end
$enddefinitions $end
#0
$dumpvars
0%
0$
0#
b0 "
0!
$end
#40000
b1 "
1%
1!
#80000
0%
0!
#120000
b10 "
1%
1!
#160000
0%
0!
#200000
b11 "
1%
1!
#240000
0%
0!
#280000
b100 "
1%
1!
#320000
0%
0!
#360000
b101 "
1%
1!
#400000
0%
0!
#440000
b110 "
1%
1!
#480000
0%
0!
#520000
b111 "
1%
1!
#560000
0%
0!
#600000
b1000 "
1%
1!
#640000
0%
0!
#680000
b1001 "
1%
1!
#720000
0%
0!
#760000
b1010 "
1%
1!
#800000
0%
0!
#840000
b1011 "
1%
1!
#880000
0%
0!
#920000
b1100 "
1%
1!
#960000
0%
0!
#1000000
b1101 "
1%
1!
#1040000
0%
0!
#1080000
b1110 "
1%
1!
#1120000
0%
0!
#1160000
b1111 "
1%
1!
#1200000
0%
0!
#1240000
b10000 "
1%
1!
#1280000
0%
0!
#1320000
b10001 "
1%
1!
#1360000
0%
0!
#1400000
b10010 "
1%
1!
#1440000
0%
0!
#1480000
b10011 "
1%
1!
#1520000
0%
0!
#1560000
b10100 "
1%
1!
#1600000
0%
0!
#1640000
b10101 "
1%
1!
#1680000
0%
0!
#1720000
b10110 "
1%
1!
#1760000
0%
0!
#1800000
b10111 "
1%
1!
#1840000
0%
0!
#1880000
b11000 "
1%
1!
#1920000
0%
0!
#1960000
b11001 "
1%
1!
#2000000
0%
0!
#2040000
b11010 "
1%
1!
#2080000
0%
0!
#2120000
b11011 "
1%
1!
#2160000
0%
0!
#2200000
b11100 "
1%
1!
#2240000
0%
0!
#2280000
b11101 "
1%
1!
#2320000
0%
0!
#2360000
b11110 "
1%
1!
#2400000
0%
0!
#2440000
b11111 "
1%
1!
#2480000
0%
0!
#2520000
b100000 "
1%
1!
#2560000
0%
0!
#2600000
b100001 "
1%
1!
#2640000
0%
0!
#2680000
b100010 "
1%
1!
#2720000
0%
0!
#2760000
b100011 "
1%
1!
#2800000
0%
0!
#2840000
b100100 "
1%
1!
#2880000
0%
0!
#2920000
b100101 "
1%
1!
#2960000
0%
0!
#3000000
b100110 "
1%
1!
#3040000
0%
0!
#3080000
b100111 "
1%
1!
#3120000
0%
0!
#3160000
b101000 "
1%
1!
#3200000
0%
0!
#3240000
b101001 "
1%
1!
#3280000
0%
0!
#3320000
b101010 "
1%
1!
#3360000
0%
0!
#3400000
b101011 "
1%
1!
#3440000
0%
0!
#3480000
b101100 "
1%
1!
#3520000
0%
0!
#3560000
b101101 "
1%
1!
#3600000
0%
0!
#3640000
b101110 "
1%
1!
#3680000
0%
0!
#3720000
b101111 "
1%
1!
#3760000
0%
0!
#3800000
b110000 "
1%
1!
#3840000
0%
0!
#3880000
b110001 "
1%
1!
#3920000
0%
0!
#3960000
b110010 "
1%
1!
#4000000
0%
0!
#4040000
b110011 "
1%
1!
#4080000
0%
0!
#4120000
b110100 "
1%
1!
#4160000
0%
0!
#4200000
b110101 "
1%
1!
#4240000
0%
0!
#4280000
b110110 "
1%
1!
#4320000
0%
0!
#4360000
b110111 "
1%
1!
#4400000
0%
0!
#4440000
b111000 "
1%
1!
#4480000
0%
0!
#4520000
b111001 "
1%
1!
#4560000
0%
0!
#4600000
b111010 "
1%
1!
#4640000
0%
0!
#4680000
b111011 "
1%
1!
#4720000
0%
0!
#4760000
b111100 "
1%
1!
#4800000
0%
0!
#4840000
b111101 "
1%
1!
#4880000
0%
0!
#4920000
b111110 "
1%
1!
#4960000
0%
0!
#5000000
b111111 "
1%
1!
#5040000
0%
0!
#5080000
b1000000 "
1%
1!
#5120000
0%
0!
#5160000
b1000001 "
1%
1!
#5200000
0%
0!
#5240000
b1000010 "
1%
1!
#5280000
0%
0!
#5320000
b1000011 "
1%
1!
#5360000
0%
0!
#5400000
b1000100 "
1%
1!
#5440000
0%
0!
#5480000
b1000101 "
1%
1!
#5520000
0%
0!
#5560000
b1000110 "
1%
1!
#5600000
0%
0!
#5640000
b1000111 "
1%
1!
#5680000
0%
0!
#5720000
b1001000 "
1%
1!
#5760000
0%
0!
#5800000
b1001001 "
1%
1!
#5840000
0%
0!
#5880000
b1001010 "
1%
1!
#5920000
0%
0!
#5960000
b1001011 "
1%
1!
#6000000
0%
0!
#6040000
b1001100 "
1%
1!
#6080000
0%
0!
#6120000
b1001101 "
1%
1!
#6160000
0%
0!
#6200000
b1001110 "
1%
1!
#6240000
0%
0!
#6280000
b1001111 "
1%
1!
#6320000
0%
0!
#6360000
b1010000 "
1%
1!
#6400000
0%
0!
#6440000
b1010001 "
1%
1!
#6480000
0%
0!
#6520000
b1010010 "
1%
1!
#6560000
0%
0!
#6600000
b1010011 "
1%
1!
#6640000
0%
0!
#6680000
b1010100 "
1%
1!
#6720000
0%
0!
#6760000
b1010101 "
1%
1!
#6800000
0%
0!
#6840000
b1010110 "
1%
1!
#6880000
0%
0!
#6920000
b1010111 "
1%
1!
#6960000
0%
0!
#7000000
b1011000 "
1%
1!
#7040000
0%
0!
#7080000
b1011001 "
1%
1!
#7120000
0%
0!
#7160000
b1011010 "
1%
1!
#7200000
0%
0!
#7240000
b1011011 "
1%
1!
#7280000
0%
0!
#7320000
b1011100 "
1%
1!
#7360000
0%
0!
#7400000
b1011101 "
1%
1!
#7440000
0%
0!
#7480000
b1011110 "
1%
1!
#7520000
0%
0!
#7560000
b1011111 "
1%
1!
#7600000
0%
0!
#7640000
b1100000 "
1%
1!
#7680000
0%
0!
#7720000
b1100001 "
1%
1!
#7760000
0%
0!
#7800000
b1100010 "
1%
1!
#7840000
0%
0!
#7880000
b1100011 "
1%
1!
#7920000
0%
0!
#7960000
b1100100 "
1%
1!
#8000000
0%
0!
#8040000
b1100101 "
1%
1!
#8080000
0%
0!
#8120000
b1100110 "
1%
1!
#8160000
0%
0!
#8200000
b1100111 "
1%
1!
#8240000
0%
0!
#8280000
b1101000 "
1%
1!
#8320000
0%
0!
#8360000
b1101001 "
1%
1!
#8400000
0%
0!
#8440000
b1101010 "
1%
1!
#8480000
0%
0!
#8520000
b1101011 "
1%
1!
#8560000
0%
0!
#8600000
b1101100 "
1%
1!
#8640000
0%
0!
#8680000
b1101101 "
1%
1!
#8720000
0%
0!
#8760000
b1101110 "
1%
1!
#8800000
0%
0!
#8840000
b1101111 "
1%
1!
#8880000
0%
0!
#8920000
b1110000 "
1%
1!
#8960000
0%
0!
#9000000
b1110001 "
1%
1!
#9040000
0%
0!
#9080000
b1110010 "
1%
1!
#9120000
0%
0!
#9160000
b1110011 "
1%
1!
#9200000
0%
0!
#9240000
b1110100 "
1%
1!
#9280000
0%
0!
#9320000
b1110101 "
1%
1!
#9360000
0%
0!
#9400000
b1110110 "
1%
1!
#9440000
0%
0!
#9480000
b1110111 "
1%
1!
#9520000
0%
0!
#9560000
b1111000 "
1%
1!
#9600000
0%
0!
#9640000
b1111001 "
1%
1!
#9680000
0%
0!
#9720000
b1111010 "
1%
1!
#9760000
0%
0!
#9800000
b1111011 "
1%
1!
#9840000
0%
0!
#9880000
b1111100 "
1%
1!
#9920000
0%
0!
#9960000
b1111101 "
1%
1!
#10000000
0%
0!
#10040000
b1111110 "
1%
1!
#10080000
0%
0!
#10120000
b1111111 "
1%
1!
#10160000
0%
0!
#10200000
b10000000 "
1%
1!
#10240000
0%
0!
#10280000
b10000001 "
1%
1!
#10320000
0%
0!
#10360000
b10000010 "
1%
1!
#10400000
0%
0!
#10440000
b10000011 "
1%
1!
#10480000
0%
0!
#10520000
b10000100 "
1%
1!
#10560000
0%
0!
#10600000
b10000101 "
1%
1!
#10640000
0%
0!
#10680000
b10000110 "
1%
1!
#10720000
0%
0!
#10760000
b10000111 "
1%
1!
#10800000
0%
0!
#10840000
b10001000 "
1%
1!
#10880000
0%
0!
#10920000
b10001001 "
1%
1!
#10960000
0%
0!
#11000000
b10001010 "
1%
1!
#11040000
0%
0!
#11080000
b10001011 "
1%
1!
#11120000
0%
0!
#11160000
b10001100 "
1%
1!
#11200000
0%
0!
#11240000
b10001101 "
1%
1!
#11280000
0%
0!
#11320000
b10001110 "
1%
1!
#11360000
0%
0!
#11400000
b10001111 "
1%
1!
#11440000
0%
0!
#11480000
b10010000 "
1%
1!
#11520000
0%
0!
#11560000
b10010001 "
1%
1!
#11600000
0%
0!
#11640000
b10010010 "
1%
1!
#11680000
0%
0!
#11720000
b10010011 "
1%
1!
#11760000
0%
0!
#11800000
b10010100 "
1%
1!
#11840000
0%
0!
#11880000
b10010101 "
1%
1!
#11920000
0%
0!
#11960000
b10010110 "
1%
1!
#12000000
0%
0!
#12040000
b10010111 "
1%
1!
#12080000
0%
0!
#12120000
b10011000 "
1%
1!
#12160000
0%
0!
#12200000
b10011001 "
1%
1!
#12240000
0%
0!
#12280000
b10011010 "
1%
1!
#12320000
0%
0!
#12360000
b10011011 "
1%
1!
#12400000
0%
0!
#12440000
b10011100 "
1%
1!
#12480000
0%
0!
#12520000
b10011101 "
1%
1!
#12560000
0%
0!
#12600000
b10011110 "
1%
1!
#12640000
0%
0!
#12680000
b10011111 "
1%
1!
#12720000
0%
0!
#12760000
b10100000 "
1%
1!
#12800000
0%
0!
#12840000
b10100001 "
1%
1!
#12880000
0%
0!
#12920000
b10100010 "
1%
1!
#12960000
0%
0!
#13000000
b10100011 "
1%
1!
#13040000
0%
0!
#13080000
b10100100 "
1%
1!
#13120000
0%
0!
#13160000
b10100101 "
1%
1!
#13200000
0%
0!
#13240000
b10100110 "
1%
1!
#13280000
0%
0!
#13320000
b10100111 "
1%
1!
#13360000
0%
0!
#13400000
b10101000 "
1%
1!
#13440000
0%
0!
#13480000
b10101001 "
1%
1!
#13520000
0%
0!
#13560000
b10101010 "
1%
1!
#13600000
0%
0!
#13640000
b10101011 "
1%
1!
#13680000
0%
0!
#13720000
b10101100 "
1%
1!
#13760000
0%
0!
#13800000
b10101101 "
1%
1!
#13840000
0%
0!
#13880000
b10101110 "
1%
1!
#13920000
0%
0!
#13960000
b10101111 "
1%
1!
#14000000
0%
0!
#14040000
b10110000 "
1%
1!
#14080000
0%
0!
#14120000
b10110001 "
1%
1!
#14160000
0%
0!
#14200000
b10110010 "
1%
1!
#14240000
0%
0!
#14280000
b10110011 "
1%
1!
#14320000
0%
0!
#14360000
b10110100 "
1%
1!
#14400000
0%
0!
#14440000
b10110101 "
1%
1!
#14480000
0%
0!
#14520000
b10110110 "
1%
1!
#14560000
0%
0!
#14600000
b10110111 "
1%
1!
#14640000
0%
0!
#14680000
b10111000 "
1%
1!
#14720000
0%
0!
#14760000
b10111001 "
1%
1!
#14800000
0%
0!
#14840000
b10111010 "
1%
1!
#14880000
0%
0!
#14920000
b10111011 "
1%
1!
#14960000
0%
0!
#15000000
b10111100 "
1%
1!
#15040000
0%
0!
#15080000
b10111101 "
1%
1!
#15120000
0%
0!
#15160000
b10111110 "
1%
1!
#15200000
0%
0!
#15240000
b10111111 "
1%
1!
#15280000
0%
0!
#15320000
b11000000 "
1%
1!
#15360000
0%
0!
#15400000
b11000001 "
1%
1!
#15440000
0%
0!
#15480000
b11000010 "
1%
1!
#15520000
0%
0!
#15560000
b11000011 "
1%
1!
#15600000
0%
0!
#15640000
b11000100 "
1%
1!
#15680000
0%
0!
#15720000
b11000101 "
1%
1!
#15760000
0%
0!
#15800000
b11000110 "
1%
1!
#15840000
0%
0!
#15880000
b11000111 "
1%
1!
#15920000
0%
0!
#15960000
b11001000 "
1%
1!
#16000000
0%
0!
#16040000
b11001001 "
1%
1!
#16080000
0%
0!
#16120000
b11001010 "
1%
1!
#16160000
0%
0!
#16200000
b11001011 "
1%
1!
#16240000
0%
0!
#16280000
b11001100 "
1%
1!
#16320000
0%
0!
#16360000
b11001101 "
1%
1!
#16400000
0%
0!
#16440000
b11001110 "
1%
1!
#16480000
0%
0!
#16520000
b11001111 "
1%
1!
#16560000
0%
0!
#16600000
b11010000 "
1%
1!
#16640000
0%
0!
#16680000
b11010001 "
1%
1!
#16720000
0%
0!
#16760000
b11010010 "
1%
1!
#16800000
0%
0!
#16840000
b11010011 "
1%
1!
#16880000
0%
0!
#16920000
b11010100 "
1%
1!
#16960000
0%
0!
#17000000
b11010101 "
1%
1!
#17040000
0%
0!
#17080000
b11010110 "
1%
1!
#17120000
0%
0!
#17160000
b11010111 "
1%
1!
#17200000
0%
0!
#17240000
b11011000 "
1%
1!
#17280000
0%
0!
#17320000
b11011001 "
1%
1!
#17360000
0%
0!
#17400000
b11011010 "
1%
1!
#17440000
0%
0!
#17480000
b11011011 "
1%
1!
#17520000
0%
0!
#17560000
b11011100 "
1%
1!
#17600000
0%
0!
#17640000
b11011101 "
1%
1!
#17680000
0%
0!
#17720000
b11011110 "
1%
1!
#17760000
0%
0!
#17800000
b11011111 "
1%
1!
#17840000
0%
0!
#17880000
b11100000 "
1%
1!
#17920000
0%
0!
#17960000
b11100001 "
1%
1!
#18000000
0%
0!
#18040000
b11100010 "
1%
1!
#18080000
0%
0!
#18120000
b11100011 "
1%
1!
#18160000
0%
0!
#18200000
b11100100 "
1%
1!
#18240000
0%
0!
#18280000
b11100101 "
1%
1!
#18320000
0%
0!
#18360000
b11100110 "
1%
1!
#18400000
0%
0!
#18440000
b11100111 "
1%
1!
#18480000
0%
0!
#18520000
b11101000 "
1%
1!
#18560000
0%
0!
#18600000
b11101001 "
1%
1!
#18640000
0%
0!
#18680000
b11101010 "
1%
1!
#18720000
0%
0!
#18760000
b11101011 "
1%
1!
#18800000
0%
0!
#18840000
b11101100 "
1%
1!
#18880000
0%
0!
#18920000
b11101101 "
1%
1!
#18960000
0%
0!
#19000000
b11101110 "
1%
1!
#19040000
0%
0!
#19080000
b11101111 "
1%
1!
#19120000
0%
0!
#19160000
b11110000 "
1%
1!
#19200000
0%
0!
#19240000
b11110001 "
1%
1!
#19280000
0%
0!
#19320000
b11110010 "
1%
1!
#19360000
0%
0!
#19400000
b11110011 "
1%
1!
#19440000
0%
0!
#19480000
b11110100 "
1%
1!
#19520000
0%
0!
#19560000
b11110101 "
1%
1!
#19600000
0%
0!
#19640000
b11110110 "
1%
1!
#19680000
0%
0!
#19720000
b11110111 "
1%
1!
#19760000
0%
0!
#19800000
b11111000 "
1%
1!
#19840000
0%
0!
#19880000
b11111001 "
1%
1!
#19920000
0%
0!
#19960000
b11111010 "
1%
1!
#20000000
0%
0!
#20040000
b11111011 "
1%
1!
#20080000
0%
0!
#20120000
b11111100 "
1%
1!
#20160000
0%
0!
#20200000
b11111101 "
1%
1!
#20240000
0%
0!
#20280000
b11111110 "
1%
1!
#20320000
0%
0!
#20360000
b11111111 "
1%
1!
#20400000
0%
0!
#20440000
b100000000 "
1%
1!
#20480000
0%
0!
#20520000
b100000001 "
1%
1!
#20560000
0%
0!
#20600000
b100000010 "
1%
1!
#20640000
0%
0!
#20680000
b100000011 "
1%
1!
#20720000
0%
0!
#20760000
b100000100 "
1%
1!
#20800000
0%
0!
#20840000
b100000101 "
1%
1!
#20880000
0%
0!
#20920000
b100000110 "
1%
1!
#20960000
0%
0!
#21000000
b100000111 "
1%
1!
#21040000
0%
0!
#21080000
b100001000 "
1%
1!
#21120000
0%
0!
#21160000
b100001001 "
1%
1!
#21200000
0%
0!
#21240000
b100001010 "
1%
1!
#21280000
0%
0!
#21320000
b100001011 "
1%
1!
#21360000
0%
0!
#21400000
b100001100 "
1%
1!
#21440000
0%
0!
#21480000
b100001101 "
1%
1!
#21520000
0%
0!
#21560000
b100001110 "
1%
1!
#21600000
0%
0!
#21640000
b100001111 "
1%
1!
#21680000
0%
0!
#21720000
b100010000 "
1%
1!
#21760000
0%
0!
#21800000
b100010001 "
1%
1!
#21840000
0%
0!
#21880000
b100010010 "
1%
1!
#21920000
0%
0!
#21960000
b100010011 "
1%
1!
#22000000
0%
0!
#22040000
b100010100 "
1%
1!
#22080000
0%
0!
#22120000
b100010101 "
1%
1!
#22160000
0%
0!
#22200000
b100010110 "
1%
1!
#22240000
0%
0!
#22280000
b100010111 "
1%
1!
#22320000
0%
0!
#22360000
b100011000 "
1%
1!
#22400000
0%
0!
#22440000
b100011001 "
1%
1!
#22480000
0%
0!
#22520000
b100011010 "
1%
1!
#22560000
0%
0!
#22600000
b100011011 "
1%
1!
#22640000
0%
0!
#22680000
b100011100 "
1%
1!
#22720000
0%
0!
#22760000
b100011101 "
1%
1!
#22800000
0%
0!
#22840000
b100011110 "
1%
1!
#22880000
0%
0!
#22920000
b100011111 "
1%
1!
#22960000
0%
0!
#23000000
b100100000 "
1%
1!
#23040000
0%
0!
#23080000
b100100001 "
1%
1!
#23120000
0%
0!
#23160000
b100100010 "
1%
1!
#23200000
0%
0!
#23240000
b100100011 "
1%
1!
#23280000
0%
0!
#23320000
b100100100 "
1%
1!
#23360000
0%
0!
#23400000
b100100101 "
1%
1!
#23440000
0%
0!
#23480000
b100100110 "
1%
1!
#23520000
0%
0!
#23560000
b100100111 "
1%
1!
#23600000
0%
0!
#23640000
b100101000 "
1%
1!
#23680000
0%
0!
#23720000
b100101001 "
1%
1!
#23760000
0%
0!
#23800000
b100101010 "
1%
1!
#23840000
0%
0!
#23880000
b100101011 "
1%
1!
#23920000
0%
0!
#23960000
b100101100 "
1%
1!
#24000000
0%
0!
#24040000
b100101101 "
1%
1!
#24080000
0%
0!
#24120000
b100101110 "
1%
1!
#24160000
0%
0!
#24200000
b100101111 "
1%
1!
#24240000
0%
0!
#24280000
b100110000 "
1%
1!
#24320000
0%
0!
#24360000
b100110001 "
1%
1!
#24400000
0%
0!
#24440000
b100110010 "
1%
1!
#24480000
0%
0!
#24520000
b100110011 "
1%
1!
#24560000
0%
0!
#24600000
b100110100 "
1%
1!
#24640000
0%
0!
#24680000
b100110101 "
1%
1!
#24720000
0%
0!
#24760000
b100110110 "
1%
1!
#24800000
0%
0!
#24840000
b100110111 "
1%
1!
#24880000
0%
0!
#24920000
b100111000 "
1%
1!
#24960000
0%
0!
#25000000
b100111001 "
1%
1!
#25040000
0%
0!
#25080000
b100111010 "
1%
1!
#25120000
0%
0!
#25160000
b100111011 "
1%
1!
#25200000
0%
0!
#25240000
b100111100 "
1%
1!
#25280000
0%
0!
#25320000
b100111101 "
1%
1!
#25360000
0%
0!
#25400000
b100111110 "
1%
1!
#25440000
0%
0!
#25480000
b100111111 "
1%
1!
#25520000
0%
0!
#25560000
b101000000 "
1%
1!
#25600000
0%
0!
#25640000
b101000001 "
1%
1!
#25680000
0%
0!
#25720000
b101000010 "
1%
1!
#25760000
0%
0!
#25800000
b101000011 "
1%
1!
#25840000
0%
0!
#25880000
b101000100 "
1%
1!
#25920000
0%
0!
#25960000
b101000101 "
1%
1!
#26000000
0%
0!
#26040000
b101000110 "
1%
1!
#26080000
0%
0!
#26120000
b101000111 "
1%
1!
#26160000
0%
0!
#26200000
b101001000 "
1%
1!
#26240000
0%
0!
#26280000
b101001001 "
1%
1!
#26320000
0%
0!
#26360000
b101001010 "
1%
1!
#26400000
0%
0!
#26440000
b101001011 "
1%
1!
#26480000
0%
0!
#26520000
b101001100 "
1%
1!
#26560000
0%
0!
#26600000
b101001101 "
1%
1!
#26640000
0%
0!
#26680000
b101001110 "
1%
1!
#26720000
0%
0!
#26760000
b101001111 "
1%
1!
#26800000
0%
0!
#26840000
b101010000 "
1%
1!
#26880000
0%
0!
#26920000
b101010001 "
1%
1!
#26960000
0%
0!
#27000000
b101010010 "
1%
1!
#27040000
0%
0!
#27080000
b101010011 "
1%
1!
#27120000
0%
0!
#27160000
b101010100 "
1%
1!
#27200000
0%
0!
#27240000
b101010101 "
1%
1!
#27280000
0%
0!
#27320000
b101010110 "
1%
1!
#27360000
0%
0!
#27400000
b101010111 "
1%
1!
#27440000
0%
0!
#27480000
b101011000 "
1%
1!
#27520000
0%
0!
#27560000
b101011001 "
1%
1!
#27600000
0%
0!
#27640000
b101011010 "
1%
1!
#27680000
0%
0!
#27720000
b101011011 "
1%
1!
#27760000
0%
0!
#27800000
b101011100 "
1%
1!
#27840000
0%
0!
#27880000
b101011101 "
1%
1!
#27920000
0%
0!
#27960000
b101011110 "
1%
1!
#28000000
0%
0!
#28040000
b101011111 "
1%
1!
#28080000
0%
0!
#28120000
b101100000 "
1%
1!
#28160000
0%
0!
#28200000
b101100001 "
1%
1!
#28240000
0%
0!
#28280000
b101100010 "
1%
1!
#28320000
0%
0!
#28360000
b101100011 "
1%
1!
#28400000
0%
0!
#28440000
b101100100 "
1%
1!
#28480000
0%
0!
#28520000
b101100101 "
1%
1!
#28560000
0%
0!
#28600000
b101100110 "
1%
1!
#28640000
0%
0!
#28680000
b101100111 "
1%
1!
#28720000
0%
0!
#28760000
b101101000 "
1%
1!
#28800000
0%
0!
#28840000
b101101001 "
1%
1!
#28880000
0%
0!
#28920000
b101101010 "
1%
1!
#28960000
0%
0!
#29000000
b101101011 "
1%
1!
#29040000
0%
0!
#29080000
b101101100 "
1%
1!
#29120000
0%
0!
#29160000
b101101101 "
1%
1!
#29200000
0%
0!
#29240000
b101101110 "
1%
1!
#29280000
0%
0!
#29320000
b101101111 "
1%
1!
#29360000
0%
0!
#29400000
b101110000 "
1%
1!
#29440000
0%
0!
#29480000
b101110001 "
1%
1!
#29520000
0%
0!
#29560000
b101110010 "
1%
1!
#29600000
0%
0!
#29640000
b101110011 "
1%
1!
#29680000
0%
0!
#29720000
b101110100 "
1%
1!
#29760000
0%
0!
#29800000
b101110101 "
1%
1!
#29840000
0%
0!
#29880000
b101110110 "
1%
1!
#29920000
0%
0!
#29960000
b101110111 "
1%
1!
#30000000
0%
0!
#30040000
b101111000 "
1%
1!
#30080000
0%
0!
#30120000
b101111001 "
1%
1!
#30160000
0%
0!
#30200000
b101111010 "
1%
1!
#30240000
0%
0!
#30280000
b101111011 "
1%
1!
#30320000
0%
0!
#30360000
b101111100 "
1%
1!
#30400000
0%
0!
#30440000
b101111101 "
1%
1!
#30480000
0%
0!
#30520000
b101111110 "
1%
1!
#30560000
0%
0!
#30600000
b101111111 "
1%
1!
#30640000
0%
0!
#30680000
b110000000 "
1%
1!
#30720000
0%
0!
#30760000
b110000001 "
1%
1!
#30800000
0%
0!
#30840000
b110000010 "
1%
1!
#30880000
0%
0!
#30920000
b110000011 "
1%
1!
#30960000
0%
0!
#31000000
b110000100 "
1%
1!
#31040000
0%
0!
#31080000
b110000101 "
1%
1!
#31120000
0%
0!
#31160000
b110000110 "
1%
1!
#31200000
0%
0!
#31240000
b110000111 "
1%
1!
#31280000
0%
0!
#31320000
b110001000 "
1%
1!
#31360000
0%
0!
#31400000
b110001001 "
1%
1!
#31440000
0%
0!
#31480000
b110001010 "
1%
1!
#31520000
0%
0!
#31560000
b110001011 "
1%
1!
#31600000
0%
0!
#31640000
b110001100 "
1%
1!
#31680000
0%
0!
#31720000
b110001101 "
1%
1!
#31760000
0%
0!
#31800000
b110001110 "
1%
1!
#31840000
0%
0!
#31880000
b110001111 "
1%
1!
#31920000
0%
0!
#31960000
b110010000 "
1%
1!
#32000000
0%
0!
#32040000
b110010001 "
1%
1!
#32080000
0%
0!
#32120000
b110010010 "
1%
1!
#32160000
0%
0!
#32200000
b110010011 "
1%
1!
#32240000
0%
0!
#32280000
b110010100 "
1%
1!
#32320000
0%
0!
#32360000
b110010101 "
1%
1!
#32400000
0%
0!
#32440000
b110010110 "
1%
1!
#32480000
0%
0!
#32520000
b110010111 "
1%
1!
#32560000
0%
0!
#32600000
b110011000 "
1%
1!
#32640000
0%
0!
#32680000
b110011001 "
1%
1!
#32720000
0%
0!
#32760000
b110011010 "
1%
1!
#32800000
0%
0!
#32840000
b110011011 "
1%
1!
#32880000
0%
0!
#32920000
b110011100 "
1%
1!
#32960000
0%
0!
#33000000
b110011101 "
1%
1!
#33040000
0%
0!
#33080000
b110011110 "
1%
1!
#33120000
0%
0!
#33160000
b110011111 "
1%
1!
#33200000
0%
0!
#33240000
b110100000 "
1%
1!
#33280000
0%
0!
#33320000
b110100001 "
1%
1!
#33360000
0%
0!
#33400000
b110100010 "
1%
1!
#33440000
0%
0!
#33480000
b110100011 "
1%
1!
#33520000
0%
0!
#33560000
b110100100 "
1%
1!
#33600000
0%
0!
#33640000
b110100101 "
1%
1!
#33680000
0%
0!
#33720000
b110100110 "
1%
1!
#33760000
0%
0!
#33800000
b110100111 "
1%
1!
#33840000
0%
0!
#33880000
b110101000 "
1%
1!
#33920000
0%
0!
#33960000
b110101001 "
1%
1!
#34000000
0%
0!
#34040000
b110101010 "
1%
1!
#34080000
0%
0!
#34120000
b110101011 "
1%
1!
#34160000
0%
0!
#34200000
b110101100 "
1%
1!
#34240000
0%
0!
#34280000
b110101101 "
1%
1!
#34320000
0%
0!
#34360000
b110101110 "
1%
1!
#34400000
0%
0!
#34440000
b110101111 "
1%
1!
#34480000
0%
0!
#34520000
b110110000 "
1%
1!
#34560000
0%
0!
#34600000
b110110001 "
1%
1!
#34640000
0%
0!
#34680000
b110110010 "
1%
1!
#34720000
0%
0!
#34760000
b110110011 "
1%
1!
#34800000
0%
0!
#34840000
b110110100 "
1%
1!
#34880000
0%
0!
#34920000
b110110101 "
1%
1!
#34960000
0%
0!
#35000000
b110110110 "
1%
1!
#35040000
0%
0!
#35080000
b110110111 "
1%
1!
#35120000
0%
0!
#35160000
b110111000 "
1%
1!
#35200000
0%
0!
#35240000
b110111001 "
1%
1!
#35280000
0%
0!
#35320000
b110111010 "
1%
1!
#35360000
0%
0!
#35400000
b110111011 "
1%
1!
#35440000
0%
0!
#35480000
b110111100 "
1%
1!
#35520000
0%
0!
#35560000
b110111101 "
1%
1!
#35600000
0%
0!
#35640000
b110111110 "
1%
1!
#35680000
0%
0!
#35720000
b110111111 "
1%
1!
#35760000
0%
0!
#35800000
b111000000 "
1%
1!
#35840000
0%
0!
#35880000
b111000001 "
1%
1!
#35920000
0%
0!
#35960000
b111000010 "
1%
1!
#36000000
0%
0!
#36040000
b111000011 "
1%
1!
#36080000
0%
0!
#36120000
b111000100 "
1%
1!
#36160000
0%
0!
#36200000
b111000101 "
1%
1!
#36240000
0%
0!
#36280000
b111000110 "
1%
1!
#36320000
0%
0!
#36360000
b111000111 "
1%
1!
#36400000
0%
0!
#36440000
b111001000 "
1%
1!
#36480000
0%
0!
#36520000
b111001001 "
1%
1!
#36560000
0%
0!
#36600000
b111001010 "
1%
1!
#36640000
0%
0!
#36680000
b111001011 "
1%
1!
#36720000
0%
0!
#36760000
b111001100 "
1%
1!
#36800000
0%
0!
#36840000
b111001101 "
1%
1!
#36880000
0%
0!
#36920000
b111001110 "
1%
1!
#36960000
0%
0!
#37000000
b111001111 "
1%
1!
#37040000
0%
0!
#37080000
b111010000 "
1%
1!
#37120000
0%
0!
#37160000
b111010001 "
1%
1!
#37200000
0%
0!
#37240000
b111010010 "
1%
1!
#37280000
0%
0!
#37320000
b111010011 "
1%
1!
#37360000
0%
0!
#37400000
b111010100 "
1%
1!
#37440000
0%
0!
#37480000
b111010101 "
1%
1!
#37520000
0%
0!
#37560000
b111010110 "
1%
1!
#37600000
0%
0!
#37640000
b111010111 "
1%
1!
#37680000
0%
0!
#37720000
b111011000 "
1%
1!
#37760000
0%
0!
#37800000
b111011001 "
1%
1!
#37840000
0%
0!
#37880000
b111011010 "
1%
1!
#37920000
0%
0!
#37960000
b111011011 "
1%
1!
#38000000
0%
0!
#38040000
b111011100 "
1%
1!
#38080000
0%
0!
#38120000
b111011101 "
1%
1!
#38160000
0%
0!
#38200000
b111011110 "
1%
1!
#38240000
0%
0!
#38280000
b111011111 "
1%
1!
#38320000
0%
0!
#38360000
b111100000 "
1%
1!
#38400000
0%
0!
#38440000
b111100001 "
1%
1!
#38480000
0%
0!
#38520000
b111100010 "
1%
1!
#38560000
0%
0!
#38600000
b111100011 "
1%
1!
#38640000
0%
0!
#38680000
b111100100 "
1%
1!
#38720000
0%
0!
#38760000
b111100101 "
1%
1!
#38800000
0%
0!
#38840000
b111100110 "
1%
1!
#38880000
0%
0!
#38920000
b111100111 "
1%
1!
#38960000
0%
0!
#39000000
b111101000 "
1%
1!
#39040000
0%
0!
#39080000
b111101001 "
1%
1!
#39120000
0%
0!
#39160000
b111101010 "
1%
1!
#39200000
0%
0!
#39240000
b111101011 "
1%
1!
#39280000
0%
0!
#39320000
b111101100 "
1%
1!
#39360000
0%
0!
#39400000
b111101101 "
1%
1!
#39440000
0%
0!
#39480000
b111101110 "
1%
1!
#39520000
0%
0!
#39560000
b111101111 "
1%
1!
#39600000
0%
0!
